fuzzy_text_classifier/AbstractTokenizer.py
fuzzy_text_classifier/FuzzySet.py
fuzzy_text_classifier/Snorm.py
fuzzy_text_classifier/TextClassifier.py
fuzzy_text_classifier/Tnorm.py
fuzzy_text_classifier/__init__.py
fuzzy_text_classifier-1.5.0.dist-info/LICENSE
fuzzy_text_classifier-1.5.0.dist-info/METADATA
fuzzy_text_classifier-1.5.0.dist-info/WHEEL
fuzzy_text_classifier-1.5.0.dist-info/top_level.txt
fuzzy_text_classifier-1.5.0.dist-info/RECORD
