Metadata-Version: 2.1
Name: fuzzy-text-classifier
Version: 1.5.0
Summary: A fuzzy classifier for natural language text
Home-page: https://github.com/raffaellopaletta/ftc
Author: Raffaello Paletta
Author-email: raffaellopaletta@gmail.com
License: UNKNOWN
Platform: UNKNOWN
Classifier: Programming Language :: Python :: 3
Classifier: License :: OSI Approved :: MIT License
Classifier: Operating System :: OS Independent
Requires-Python: >=3.6
